{"index.md":"CcRto8QS","sendung_musik.md":"Bdxe0tAV","wiki_abenteurer.md":"C2i2vVVD","wiki_npc.md":"VKooDkRp","wiki_index.md":"DZ2VwGVY","wiki_intro.md":"BLRpJcFM","wiki_items.md":"Cv_fvvmD","wiki_karte.md":"C3TaU2Ch","wiki_klassen.md":"DMP2NKS0","wiki_wuerfel.md":"jh6Ts9Sh","wiki_waffen.md":"DJDE6c4V","wiki_gegner.md":"Bf5g0nDM","wiki_regionen.md":"CSkAa-wv","sendung_videos.md":"E6Dbdo4I","sendung_stream.md":"DK628WtN","wiki_lore.md":"D42WjAAg","wiki_geschichte.md":"C9m2fFky","wiki_völker.md":"wiJBgBgc","wiki_orte.md":"CF6DKp2K","sendung_bts.md":"BsUXxIHo","sendung_credits.md":"C0kcqzBH","wiki_gesinnung.md":"CUrP5jJF","sendung_clips.md":"yvc3Ptc1","wiki_erstellen.md":"CN8s7W42"}
